[
  {
    "medalTradePickupMstId": 2,
    "medalTradeSeriesMstId": 3,
    "objectType": 2,
    "objectId": 107,
    "pickupSkillType": 3,
    "num": 1,
    "startTime": 1483196400,
    "endTime": 1594187999,
    "isDeleted": false
  },
  {
    "medalTradePickupMstId": 3,
    "medalTradeSeriesMstId": 3,
    "objectType": 2,
    "objectId": 581,
    "pickupSkillType": 1,
    "num": 1,
    "startTime": 1594188000,
    "endTime": 1594619999,
    "isDeleted": false
  },
  {
    "medalTradePickupMstId": 4,
    "medalTradeSeriesMstId": 3,
    "objectType": 2,
    "objectId": 647,
    "pickupSkillType": 1,
    "num": 1,
    "startTime": 1594620000,
    "endTime": 1595397599,
    "isDeleted": false
  },
  {
    "medalTradePickupMstId": 7,
    "medalTradeSeriesMstId": 3,
    "objectType": 2,
    "objectId": 745,
    "pickupSkillType": 1,
    "num": 1,
    "startTime": 1595397600,
    "endTime": 1596088799,
    "isDeleted": false
  },
  {
    "medalTradePickupMstId": 8,
    "medalTradeSeriesMstId": 8,
    "objectType": 2,
    "objectId": 775,
    "pickupSkillType": 1,
    "num": 1,
    "startTime": 1596088800,
    "endTime": 1596693599,
    "isDeleted": false
  },
  {
    "medalTradePickupMstId": 11,
    "medalTradeSeriesMstId": 12,
    "objectType": 2,
    "objectId": 811,
    "pickupSkillType": 1,
    "num": 1,
    "startTime": 1594879200,
    "endTime": 1595829599,
    "isDeleted": false
  },
  {
    "medalTradePickupMstId": 12,
    "medalTradeSeriesMstId": 12,
    "objectType": 2,
    "objectId": 927,
    "pickupSkillType": 1,
    "num": 1,
    "startTime": 1595829600,
    "endTime": 1597330799,
    "isDeleted": false
  },
  {
    "medalTradePickupMstId": 13,
    "medalTradeSeriesMstId": 8,
    "objectType": 2,
    "objectId": 787,
    "pickupSkillType": 1,
    "num": 1,
    "startTime": 1596693600,
    "endTime": 1597903199,
    "isDeleted": false
  },
  {
    "medalTradePickupMstId": 19,
    "medalTradeSeriesMstId": 4,
    "objectType": 2,
    "objectId": 1095,
    "pickupSkillType": 1,
    "num": 1,
    "startTime": 1596603600,
    "endTime": 1924959599,
    "isDeleted": false
  },
  {
    "medalTradePickupMstId": 94,
    "medalTradeSeriesMstId": 69,
    "objectType": 2,
    "objectId": 3095,
    "pickupSkillType": 1,
    "num": 1,
    "startTime": 1596693600,
    "endTime": 1598540399,
    "isDeleted": false
  }
]